django_clerk_users/__init__.py
django_clerk_users/apps.py
django_clerk_users/caching.py
django_clerk_users/client.py
django_clerk_users/decorators.py
django_clerk_users/exceptions.py
django_clerk_users/managers.py
django_clerk_users/models.py
django_clerk_users/settings.py
django_clerk_users/testing.py
django_clerk_users/utils.py
django_clerk_users/authentication/__init__.py
django_clerk_users/authentication/backends.py
django_clerk_users/authentication/drf.py
django_clerk_users/authentication/utils.py
django_clerk_users/management/__init__.py
django_clerk_users/management/commands/__init__.py
django_clerk_users/management/commands/migrate_users_to_clerk.py
django_clerk_users/management/commands/sync_clerk_organizations.py
django_clerk_users/management/commands/sync_clerk_users.py
django_clerk_users/middleware/__init__.py
django_clerk_users/middleware/auth.py
django_clerk_users/migrations/0001_initial.py
django_clerk_users/migrations/0002_make_clerk_id_nullable.py
django_clerk_users/migrations/__init__.py
django_clerk_users/organizations/__init__.py
django_clerk_users/organizations/admin.py
django_clerk_users/organizations/apps.py
django_clerk_users/organizations/middleware.py
django_clerk_users/organizations/models.py
django_clerk_users/organizations/webhooks.py
django_clerk_users/organizations/migrations/0001_initial.py
django_clerk_users/organizations/migrations/__init__.py
django_clerk_users/webhooks/__init__.py
django_clerk_users/webhooks/handlers.py
django_clerk_users/webhooks/security.py
django_clerk_users/webhooks/signals.py
django_clerk_users/webhooks/views.py
django_clerk_users-0.1.3.dist-info/METADATA
django_clerk_users-0.1.3.dist-info/WHEEL
django_clerk_users-0.1.3.dist-info/licenses/LICENSE
django_clerk_users-0.1.3.dist-info/RECORD
