Metadata-Version: 2.4
Name: django-clerk-users
Version: 0.1.3
Summary: Integrate Clerk with Django
Project-URL: Changelog, https://github.com/jmitchel3/django-clerk-users
Project-URL: Documentation, https://github.com/jmitchel3/django-clerk-users
Project-URL: Funding, https://github.com/jmitchel3/django-clerk-users
Project-URL: Repository, https://github.com/jmitchel3/django-clerk-users
License-File: LICENSE
Classifier: Development Status :: 4 - Beta
Classifier: Framework :: Django
Classifier: Framework :: Django :: 4.2
Classifier: Programming Language :: Python :: 3 :: Only
Classifier: Programming Language :: Python :: 3.12
Classifier: Programming Language :: Python :: 3.13
Classifier: Programming Language :: Python :: 3.14
Requires-Python: >=3.12
Requires-Dist: clerk-backend-api>=1.0.0
Requires-Dist: django>=4.2
Requires-Dist: svix>=1.0.0
Provides-Extra: drf
Requires-Dist: djangorestframework>=3.14; extra == 'drf'
